LICENSE
MANIFEST.in
README.md
setup.py
silzila/.env
silzila/__init__.py
silzila/sqlite3.db
silzila.egg-info/PKG-INFO
silzila.egg-info/SOURCES.txt
silzila.egg-info/dependency_links.txt
silzila.egg-info/entry_points.txt
silzila.egg-info/requires.txt
silzila.egg-info/top_level.txt
silzila/app/__init__.py
silzila/app/app.py
silzila/data_connection/__init__.py
silzila/data_connection/api.py
silzila/data_connection/auth.py
silzila/data_connection/db_libraries.py
silzila/data_connection/engine.py
silzila/data_connection/model.py
silzila/data_connection/schema.py
silzila/data_connection/service.py
silzila/data_set/__init__.py
silzila/data_set/api.py
silzila/data_set/model.py
silzila/data_set/schema.py
silzila/data_set/service.py
silzila/database/__init__.py
silzila/database/config.py
silzila/database/service.py
silzila/main/__init__.py
silzila/main/__main__.py
silzila/play_book/__init__.py
silzila/play_book/api.py
silzila/play_book/model.py
silzila/play_book/schema.py
silzila/play_book/service.py
silzila/query_builder/__init__.py
silzila/query_builder/query_composer.py
silzila/query_builder/query_composer_filter.py
silzila/query_builder/relationship.py
silzila/query_builder/schema_recursive_search.py
silzila/query_builder/sql_dialect/__init__.py
silzila/query_builder/sql_dialect/common_where.py
silzila/query_builder/sql_dialect/filter_mssql.py
silzila/query_builder/sql_dialect/filter_mysql.py
silzila/query_builder/sql_dialect/filter_postgres.py
silzila/query_builder/sql_dialect/helper_function.py
silzila/query_builder/sql_dialect/select_mssql.py
silzila/query_builder/sql_dialect/select_mysql.py
silzila/query_builder/sql_dialect/select_postgres.py
silzila/static/asset-manifest.json
silzila/static/favicon.ico
silzila/static/favicon.png
silzila/static/index.html
silzila/static/logo192.png
silzila/static/logo512.png
silzila/static/manifest.json
silzila/static/robots.txt
silzila/static/static/css/main.fb00fad7.css
silzila/static/static/css/main.fb00fad7.css.map
silzila/static/static/js/787.3a81f7d8.chunk.js
silzila/static/static/js/787.3a81f7d8.chunk.js.map
silzila/static/static/js/main.4d180d7d.js
silzila/static/static/js/main.4d180d7d.js.LICENSE.txt
