Metadata-Version: 2.1
Name: silzila
Version: 0.1.1
Summary: App for Dashboarding & Data Exploration
Author: Balu Mahendran
Author-email: mail@silzila.org
License: UNKNOWN
Platform: UNKNOWN
Classifier: Programming Language :: Python :: 3
Classifier: License :: OSI Approved :: MIT License
Classifier: Operating System :: OS Independent
Requires-Python: >=3.7
License-File: LICENSE
